{"text": "\ud83d\udc98\ud83d\ude0d\u2764 #ilikehim #ilovehim #Moonlight #Hawaii #hawaiifive0 #mickstjohn #stevemcgarrett #USA #amerika #AlexOLoughlin https://t.co/2cJba40HM7", "coordinates": null, "place": {"bounding_box": {"type": "Polygon", "coordinates": [[[16.411691, 47.987554], [16.411691, 48.038991], [16.486147, 48.038991], [16.486147, 47.987554]]]}, "name": "Moosbrunn", "country": "\u00d6sterreich", "full_name": "Moosbrunn, \u00d6sterreich", "country_code": "AT"}, "created_at": "Sun May 20 10:42:32 +0000 2018", "sentiment": 0.0}
{"text": "\ud83d\udc98\ud83d\ude0d\u2764 #ilikehim #ilovehim #Moonlight #Hawaii #hawaiifive0 #mickstjohn #stevemcgarrett #USA #amerika #AlexOLoughlin https://t.co/gnFH0CPfNA", "coordinates": null, "place": {"bounding_box": {"type": "Polygon", "coordinates": [[[16.411691, 47.987554], [16.411691, 48.038991], [16.486147, 48.038991], [16.486147, 47.987554]]]}, "name": "Moosbrunn", "country": "\u00d6sterreich", "full_name": "Moosbrunn, \u00d6sterreich", "country_code": "AT"}, "created_at": "Sun May 20 10:43:31 +0000 2018", "sentiment": 0.0}
{"text": "\ud83d\udc98\ud83d\ude0d\u2764 #ilikehim #ilovehim #Moonlight #Hawaii #hawaiifive0 #mickstjohn #stevemcgarrett #USA #amerika #AlexOLoughlin https://t.co/OifZhtIPP8", "coordinates": null, "place": {"bounding_box": {"type": "Polygon", "coordinates": [[[16.411691, 47.987554], [16.411691, 48.038991], [16.486147, 48.038991], [16.486147, 47.987554]]]}, "name": "Moosbrunn", "country": "\u00d6sterreich", "full_name": "Moosbrunn, \u00d6sterreich", "country_code": "AT"}, "created_at": "Sun May 20 15:55:52 +0000 2018", "sentiment": 0.0}
{"text": "Tam bir katil amerika  soytar\u0131s\u0131 ermeni https://t.co/VSGv0XJR6L", "coordinates": null, "place": {"bounding_box": {"type": "Polygon", "coordinates": [[[15.868086, 46.945796], [15.868086, 46.962623], [15.914978, 46.962623], [15.914978, 46.945796]]]}, "name": "Feldbach", "country": "\u00d6sterreich", "full_name": "Feldbach, \u00d6sterreich", "country_code": "AT"}, "created_at": "Sun May 20 16:38:00 +0000 2018", "sentiment": 0.0}
{"text": "\ud83d\udc98\ud83d\ude0d\u2764 #ilikehim #ilovehim #Moonlight #Hawaii #hawaiifive0 #mickstjohn #stevemcgarrett #USA #amerika #AlexOLoughlin https://t.co/rwUCBxZ5Rz", "coordinates": null, "place": {"bounding_box": {"type": "Polygon", "coordinates": [[[16.411691, 47.987554], [16.411691, 48.038991], [16.486147, 48.038991], [16.486147, 47.987554]]]}, "name": "Moosbrunn", "country": "\u00d6sterreich", "full_name": "Moosbrunn, \u00d6sterreich", "country_code": "AT"}, "created_at": "Sun May 20 21:25:00 +0000 2018", "sentiment": 0.0}
{"text": "\ud83d\udc98\ud83d\ude0d\u2764 #ilikehim #ilovehim #Moonlight #Hawaii #hawaiifive0 #mickstjohn #stevemcgarrett #USA #amerika #AlexOLoughlin https://t.co/Wb3YhvfdoL", "coordinates": null, "place": {"bounding_box": {"type": "Polygon", "coordinates": [[[16.411691, 47.987554], [16.411691, 48.038991], [16.486147, 48.038991], [16.486147, 47.987554]]]}, "name": "Moosbrunn", "country": "\u00d6sterreich", "full_name": "Moosbrunn, \u00d6sterreich", "country_code": "AT"}, "created_at": "Mon May 21 09:47:13 +0000 2018", "sentiment": 0.0}
{"text": "\ud83d\udc98\ud83d\ude0d\u2764 #ilikehim #ilovehim #Moonlight #Hawaii #hawaiifive0 #mickstjohn #stevemcgarrett #USA #amerika #AlexOLoughlin https://t.co/cCsadOt5ci", "coordinates": null, "place": {"bounding_box": {"type": "Polygon", "coordinates": [[[16.411691, 47.987554], [16.411691, 48.038991], [16.486147, 48.038991], [16.486147, 47.987554]]]}, "name": "Moosbrunn", "country": "\u00d6sterreich", "full_name": "Moosbrunn, \u00d6sterreich", "country_code": "AT"}, "created_at": "Mon May 21 10:49:24 +0000 2018", "sentiment": 0.0}
{"text": "\ud83d\udc98\ud83d\ude0d\u2764 #ilikehim #ilovehim #Moonlight #Hawaii #hawaiifive0 #mickstjohn #stevemcgarrett #USA #amerika #AlexOLoughlin\u2026 https://t.co/x0hijGRkwb", "coordinates": null, "place": {"bounding_box": {"type": "Polygon", "coordinates": [[[16.411691, 47.987554], [16.411691, 48.038991], [16.486147, 48.038991], [16.486147, 47.987554]]]}, "name": "Moosbrunn", "country": "\u00d6sterreich", "full_name": "Moosbrunn, \u00d6sterreich", "country_code": "AT"}, "created_at": "Fri May 25 20:31:25 +0000 2018", "sentiment": 0.0}
{"text": "\ud83d\udc98\ud83d\ude0d\u2764 #ilikehim #ilovehim #Moonlight #Hawaii #hawaiifive0 #mickstjohn #stevemcgarrett #USA #amerika #AlexOLoughlin https://t.co/OSEaNddU56", "coordinates": null, "place": {"bounding_box": {"type": "Polygon", "coordinates": [[[16.411691, 47.987554], [16.411691, 48.038991], [16.486147, 48.038991], [16.486147, 47.987554]]]}, "name": "Moosbrunn", "country": "\u00d6sterreich", "full_name": "Moosbrunn, \u00d6sterreich", "country_code": "AT"}, "created_at": "Sat May 26 09:33:58 +0000 2018", "sentiment": 0.0}
{"text": "\ud83d\udc98\ud83d\ude0d\u2764 #ilikehim #ilovehim #Moonlight #Hawaii #hawaiifive0 #mickstjohn #stevemcgarrett #USA #amerika #AlexOLoughlin https://t.co/o5igZXEO9D", "coordinates": null, "place": {"bounding_box": {"type": "Polygon", "coordinates": [[[16.411691, 47.987554], [16.411691, 48.038991], [16.486147, 48.038991], [16.486147, 47.987554]]]}, "name": "Moosbrunn", "country": "\u00d6sterreich", "full_name": "Moosbrunn, \u00d6sterreich", "country_code": "AT"}, "created_at": "Sat May 26 09:48:37 +0000 2018", "sentiment": 0.0}
{"text": "\ud83d\udc98\ud83d\ude0d\u2764 #ilikehim #ilovehim #Moonlight #Hawaii #hawaiifive0 #mickstjohn #stevemcgarrett #USA #amerika #AlexOLoughlin https://t.co/Uef0dZtm6V", "coordinates": null, "place": {"bounding_box": {"type": "Polygon", "coordinates": [[[16.411691, 47.987554], [16.411691, 48.038991], [16.486147, 48.038991], [16.486147, 47.987554]]]}, "name": "Moosbrunn", "country": "\u00d6sterreich", "full_name": "Moosbrunn, \u00d6sterreich", "country_code": "AT"}, "created_at": "Sat May 26 09:50:48 +0000 2018", "sentiment": 0.0}
{"text": "\ud83d\udc98\ud83d\ude0d\u2764 #ilikehim #ilovehim #Moonlight #Hawaii #hawaiifive0 #mickstjohn #stevemcgarrett #USA #amerika #AlexOLoughlin\u2026 https://t.co/XOC8kqW3bm", "coordinates": null, "place": {"bounding_box": {"type": "Polygon", "coordinates": [[[16.411691, 47.987554], [16.411691, 48.038991], [16.486147, 48.038991], [16.486147, 47.987554]]]}, "name": "Moosbrunn", "country": "\u00d6sterreich", "full_name": "Moosbrunn, \u00d6sterreich", "country_code": "AT"}, "created_at": "Sat May 26 19:20:10 +0000 2018", "sentiment": 0.0}
{"text": "\ud83d\udc98\ud83d\ude0d\u2764 #ilikehim #ilovehim #Moonlight #Hawaii #hawaiifive0 #mickstjohn #stevemcgarrett #USA #amerika #AlexOLoughlin https://t.co/r6SZeMnk1g", "coordinates": null, "place": {"bounding_box": {"type": "Polygon", "coordinates": [[[9.530787, 46.372299], [9.530787, 49.020712], [17.160749, 49.020712], [17.160749, 46.372299]]]}, "name": "\u00d6sterreich", "country": "\u00d6sterreich", "full_name": "\u00d6sterreich", "country_code": "AT"}, "created_at": "Wed May 30 15:33:11 +0000 2018", "sentiment": 0.0}
